WebScreens/__init__.py
WebScreens/version.py
WebScreens/web.py
robotframework_webscreens-0.1.1.dist-info/LICENSE
robotframework_webscreens-0.1.1.dist-info/METADATA
robotframework_webscreens-0.1.1.dist-info/WHEEL
robotframework_webscreens-0.1.1.dist-info/top_level.txt
robotframework_webscreens-0.1.1.dist-info/RECORD
